odoo_deets/__init__.py
odoo_deets/config.py
odoo_deets/main.py
odoo_deets/odoo_deets.toml
odoo_deets/profiler.py
odoo_deets/renderer.py
odoo_deets/styles.css
odoo_deets/utils.py
odoo_deets/analysis/__init__.py
odoo_deets/analysis/mem_by_field.py
odoo_deets/analysis/mem_by_model.py
odoo_deets/analysis/mem_by_record.py
odoo_deets-0.1.5.dist-info/entry_points.txt
odoo_deets-0.1.5.dist-info/WHEEL
odoo_deets-0.1.5.dist-info/METADATA
odoo_deets-0.1.5.dist-info/RECORD
