Metadata-Version: 2.4
Name: odoo_deets
Version: 0.1.5
Summary: Memory profiling for Odoo
Author-email: Austin Paskerian <paau@odoo.com>
Requires-Python: >=3.10
Requires-Dist: pygal>=3.0.1
Requires-Dist: pympler>=1.1
Requires-Dist: click>=8.1
Requires-Dist: tomli-w>=1.2.0
Requires-Dist: lxml
